eventual_rmq/__init__.py
eventual_rmq/broker.py
eventual_rmq-0.5.0.dist-info/WHEEL
eventual_rmq-0.5.0.dist-info/METADATA
eventual_rmq-0.5.0.dist-info/RECORD
